{
  "songs": [
    {
      "id": 2,
      "title": "song 2",
      "lyrics": "song lyrics",
      "notes": "some notes",
      "comments": []
    },
    {
      "id": 3,
      "title": "song 3",
      "lyrics": "song lyrics \n more lyrics \n more lyrics",
      "notes": "some notes",
      "comments": []
    }
  ],
  "comments": [
    {
      "id": 9,
      "body": "I don't think that's a good idea.",
      "timeStamp": "2017-09-24T18:25:35.939Z",
      "author": "Ryan"
    },
    {
      "id": 10,
      "body": "Another comment.",
      "timeStamp": "2017-09-25T02:37:03.569Z",
      "author": "Ryan"
    },
    {
      "id": 11,
      "body": "It's cool you can comment on the songs.",
      "timeStamp": "2017-09-25T02:37:33.267Z",
      "author": "Ryan"
    },
    {
      "id": 12,
      "body": "I like this one.",
      "timeStamp": "2017-09-26T03:36:22.624Z",
      "author": "Ryan"
    }
  ],
  "profile": {
    "name": "typicode"
  }
}